{
  "life": "life",
  "you": "you",
  "heart": "heart",
  "eart ": "heart",
  "function": "function",
  "hot": "hrt",
  "hrt": "hrt",
  "heart disease": "heart disease",
  "coronary artery disease": "coronary artery disease",
  "cad": "CAD",
  "oronary artery disease?": "coronary artery disease",
  "ecg": "ECG",
  "cg?": "ECG",
  "electrocardiogram": "electrocardiogram",
  "blood pressure": "blood pressure",
  "lood pressure?": "blood pressure",
  "heart attack": "heart attack",
  "eart attack?": "heart attack",
  "hart attack": "hart attack",
  "hot attack": "hrt attack",
  "hrt attack": "hrt attack",
  "aspirin": "aspirin",
  "hot disease": "hrt disease",
  "hrt disease": "hrt disease",
  "cholestrol ": "cholesterol",
  "cholesterol": "cholesterol",
  "holestrol l": "cholesterol",
  "heart health": "heart health",
  "eart health?": "heart health",
  "hart health": "hart health",
  "ot health?": "hrt health",
  "hrt health": "hrt health",
  "exercise": "exercise",
  "cards ": "cardio",
  "cardio": "cardio",
  "xercise ": "exercise",
  "smoking": "smoking",
  "moking ": "smoking",
  "risks": "risks",
  "arrhythmia": "arrhythmia",
  "rrhythmia?": "arrhythmia",
  "symptoms": "symptoms",
  "heart failure": "heart failure",
  "eart failure?": "heart failure",
  "cardiomyopathy": "cardiomyopathy",
  "ardiomyopathy?": "cardiomyopathy",
  "echocardiogram": "echocardiogram",
  "chocardiogram ": "echocardiogram",
  "stress test": "stress test",
  "term": "term",
  "erm?": "term",
  "erm ": "term",
  "test/procedure": "test/procedure",
  "disease": "disease",
  "condition": "condition",
  "ondition?": "condition",
  "ondition ": "condition",
  "factor": "factor",
  "actor ": "factor",
  "lifestyle factor": "lifestyle factor",
  "chest": "chest",
  "left side of the chest": "left side of the chest",
  "chest pain": "chest pain"
}